blexus/__init__.py
blexus/blexus.py
tests/__init__.py
tests/test_blexus.py
blexus-0.0.6.dist-info/LICENSE
blexus-0.0.6.dist-info/METADATA
blexus-0.0.6.dist-info/WHEEL
blexus-0.0.6.dist-info/top_level.txt
blexus-0.0.6.dist-info/RECORD
