Metadata-Version: 2.1
Name: blexus
Version: 0.0.6
Summary: Blexus official package
Home-page: https://github.com/Blexus-org/pkg
Author: Blexus
Author-email: mmmmmm505090@gmail.com
Classifier: Programming Language :: Python :: 3
Classifier: License :: OSI Approved :: MIT License
Classifier: Operating System :: OS Independent
Requires-Python: >=3.6
License-File: LICENSE
